bldgkit.py
bldgkit-0.0.1.dist-info/LICENSE
bldgkit-0.0.1.dist-info/METADATA
bldgkit-0.0.1.dist-info/WHEEL
bldgkit-0.0.1.dist-info/top_level.txt
bldgkit-0.0.1.dist-info/RECORD
