Metadata-Version: 2.1
Name: bldgkit
Version: 0.0.1
Summary: BLDGKIT geometry library
Author: Danil Nagy
Classifier: Programming Language :: Python :: 3
Classifier: License :: OSI Approved :: MIT License
Classifier: Operating System :: OS Independent
Requires-Python: >=3.6
License-File: LICENSE
